[
    {
        "id": 0,
        "status": "delivered",
        "date": "2022/12/15",
        "final_price": 20,
        "items": [
            {
                "id": "00",
                "quantity": 1,
                "price": 10
            },
            {
                "id": "01",
                "quantity": 1,
                "price": 10
            }
        ]
    },
    {
        "id": 1,
        "status": "a caminho",
        "date": "2022/12/15",
        "final_price": 10,
        "items": [
            {
                "id": "10",
                "quanitity": 2,
                "price": 5
            }
        ]
    },
    {
        "id": 2,
        "status": "payment pending",
        "date": "2022/12/15",
        "final_price": 20,
        "items": [
            {
                "id": "20",
                "quantity": 1,
                "price": 10
            },
            {
                "id": "21",
                "quantity": 1,
                "price": 10
            }
        ]
    },
    {
        "id": 3,
        "status": "processing",
        "date": "2022/12/15",
        "final_price": 20,
        "items": [
            {
                "id": "30",
                "quantity": 1,
                "price": 10
            },
            {
                "id": "31",
                "quantity": 1,
                "price": 10
            }
        ]
  
    },
    {
        "id": 4,
        "status": "delivered",
        "date": "2022/12/15",
        "final_price": 10,
        "items": [
            {
                "id": "40",
                "quantity": 1,
                "price": 10
            }
        ]
    }
]